hanyu_gui/__init__.py
hanyu_gui/main_window.py
hanyu_lang/__init__.py
hanyu_lang/accelerate.c
hanyu_lang/cli.py
hanyu_lang/lexer.py
hanyu_lang/parser.py
hanyu_lang/runtime.py
hanyu_lang/typing.py
hanyu_lang/runtime/__init__.py
hanyu_lang/runtime/interpreter.py
hanyu_lang-0.1.2.dist-info/licenses/LICENSE
hanyu_lang-0.1.2.dist-info/METADATA
hanyu_lang-0.1.2.dist-info/WHEEL
hanyu_lang-0.1.2.dist-info/entry_points.txt
hanyu_lang-0.1.2.dist-info/top_level.txt
hanyu_lang-0.1.2.dist-info/RECORD
