Metadata-Version: 2.4
Name: hanyu-lang
Version: 0.1.2
Summary: 汉语编程语言实现
Home-page: https://github.com/yourusername/hanyu-lang
Author: 你的名字/团队名
Author-email: your.email@example.com
License: MIT
Classifier: Development Status :: 3 - Alpha
Classifier: Intended Audience :: Developers
Classifier: License :: OSI Approved :: MIT License
Classifier: Natural Language :: Chinese (Simplified)
Classifier: Programming Language :: Python :: 3.8
Classifier: Topic :: Software Development :: Compilers
Requires-Python: >=3.8
License-File: LICENSE
Requires-Dist: pygments>=2.7
Requires-Dist: watchdog>=2.0
Requires-Dist: tkinterweb>=3.11
Provides-Extra: secure
Requires-Dist: pyjwt>=2.0; extra == "secure"
Requires-Dist: cryptography>=3.4; extra == "secure"
Provides-Extra: full
Requires-Dist: numpy>=1.21; extra == "full"
Requires-Dist: pandas>=1.3; extra == "full"
Dynamic: author
Dynamic: author-email
Dynamic: classifier
Dynamic: description
Dynamic: description-content-type
Dynamic: home-page
Dynamic: license
Dynamic: license-file
Dynamic: provides-extra
Dynamic: requires-dist
Dynamic: requires-python
Dynamic: summary
